FaceIn/FaceIn.py
FaceIn/FaceIn_BuildDatabase.py
testing/test_csicamera.py
testing/test_detectface.py
testing/test_keyinput.py
testing/test_mtcnn.py
testing/test_retinaface.py
testing/test_tk.py
FaceIn-1.0.1.dist-info/LICENSE
FaceIn-1.0.1.dist-info/METADATA
FaceIn-1.0.1.dist-info/WHEEL
FaceIn-1.0.1.dist-info/top_level.txt
FaceIn-1.0.1.dist-info/RECORD
