Metadata-Version: 2.1
Name: FaceIn
Version: 1.0.1
Summary: Classroom visual sign in program
Home-page: https://github.com/uutzinger/FaceIn
Author: Urs Utzinger
Author-email: uutzinger@gmail.com
License: MIT
Keywords: face detection,face recognition
Platform: UNKNOWN
Classifier: Development Status :: 4 - Beta
Classifier: Intended Audience :: Education 
Classifier: Topic :: Multimedia :: Video :: Capture
Classifier: License :: OSI Approved :: MIT License
Classifier: Programming Language :: Python :: 3
License-File: LICENSE
